{
    "s1": [
        {
            "rx_packets": 0,
            "tx_packets": 0,
            "rx_bytes": 0,
            "tx_bytes": 0,
            "rx_dropped": 3,
            "tx_dropped": 0,
            "rx_errors": 0,
            "tx_errors": 0,
            "rx_frame_err": 0,
            "rx_over_err": 0,
            "rx_crc_err": 0,
            "collisions": 0,
            "duration_sec": 22,
            "duration_nsec": 421000000,
            "port_no": "LOCAL"
        },
        {
            "rx_packets": 167,
            "tx_packets": 71,
            "rx_bytes": 78174,
            "tx_bytes": 6307,
            "rx_dropped": 0,
            "tx_dropped": 0,
            "rx_errors": 0,
            "tx_errors": 0,
            "rx_frame_err": 0,
            "rx_over_err": 0,
            "rx_crc_err": 0,
            "collisions": 0,
            "duration_sec": 22,
            "duration_nsec": 426000000,
            "port_no": 1
        },
        {
            "rx_packets": 55,
            "tx_packets": 53,
            "rx_bytes": 5157,
            "tx_bytes": 5073,
            "rx_dropped": 0,
            "tx_dropped": 0,
            "rx_errors": 0,
            "tx_errors": 0,
            "rx_frame_err": 0,
            "rx_over_err": 0,
            "rx_crc_err": 0,
            "collisions": 0,
            "duration_sec": 22,
            "duration_nsec": 426000000,
            "port_no": 2
        },
        {
            "rx_packets": 70,
            "tx_packets": 204,
            "rx_bytes": 6189,
            "tx_bytes": 82031,
            "rx_dropped": 0,
            "tx_dropped": 0,
            "rx_errors": 0,
            "tx_errors": 0,
            "rx_frame_err": 0,
            "rx_over_err": 0,
            "rx_crc_err": 0,
            "collisions": 0,
            "duration_sec": 22,
            "duration_nsec": 426000000,
            "port_no": 3
        }
    ],
    "s2": [
        {
            "rx_packets": 0,
            "tx_packets": 0,
            "rx_bytes": 0,
            "tx_bytes": 0,
            "rx_dropped": 6,
            "tx_dropped": 0,
            "rx_errors": 0,
            "tx_errors": 0,
            "rx_frame_err": 0,
            "rx_over_err": 0,
            "rx_crc_err": 0,
            "collisions": 0,
            "duration_sec": 22,
            "duration_nsec": 410000000,
            "port_no": "LOCAL"
        },
        {
            "rx_packets": 146,
            "tx_packets": 72,
            "rx_bytes": 65516,
            "tx_bytes": 6367,
            "rx_dropped": 0,
            "tx_dropped": 0,
            "rx_errors": 0,
            "tx_errors": 0,
            "rx_frame_err": 0,
            "rx_over_err": 0,
            "rx_crc_err": 0,
            "collisions": 0,
            "duration_sec": 22,
            "duration_nsec": 418000000,
            "port_no": 1
        },
        {
            "rx_packets": 53,
            "tx_packets": 55,
            "rx_bytes": 5073,
            "tx_bytes": 5157,
            "rx_dropped": 0,
            "tx_dropped": 0,
            "rx_errors": 0,
            "tx_errors": 0,
            "rx_frame_err": 0,
            "rx_over_err": 0,
            "rx_crc_err": 0,
            "collisions": 0,
            "duration_sec": 22,
            "duration_nsec": 419000000,
            "port_no": 2
        },
        {
            "rx_packets": 66,
            "tx_packets": 181,
            "rx_bytes": 6021,
            "tx_bytes": 69289,
            "rx_dropped": 0,
            "tx_dropped": 0,
            "rx_errors": 0,
            "tx_errors": 0,
            "rx_frame_err": 0,
            "rx_over_err": 0,
            "rx_crc_err": 0,
            "collisions": 0,
            "duration_sec": 22,
            "duration_nsec": 419000000,
            "port_no": 3
        }
    ],
    "s3": [
        {
            "rx_packets": 0,
            "tx_packets": 0,
            "rx_bytes": 0,
            "tx_bytes": 0,
            "rx_dropped": 6,
            "tx_dropped": 0,
            "rx_errors": 0,
            "tx_errors": 0,
            "rx_frame_err": 0,
            "rx_over_err": 0,
            "rx_crc_err": 0,
            "collisions": 0,
            "duration_sec": 22,
            "duration_nsec": 425000000,
            "port_no": "LOCAL"
        },
        {
            "rx_packets": 204,
            "tx_packets": 70,
            "rx_bytes": 82031,
            "tx_bytes": 6189,
            "rx_dropped": 0,
            "tx_dropped": 0,
            "rx_errors": 0,
            "tx_errors": 0,
            "rx_frame_err": 0,
            "rx_over_err": 0,
            "rx_crc_err": 0,
            "collisions": 0,
            "duration_sec": 22,
            "duration_nsec": 429000000,
            "port_no": 4
        },
        {
            "rx_packets": 30,
            "tx_packets": 208,
            "rx_bytes": 2188,
            "tx_bytes": 80775,
            "rx_dropped": 0,
            "tx_dropped": 0,
            "rx_errors": 0,
            "tx_errors": 0,
            "rx_frame_err": 0,
            "rx_over_err": 0,
            "rx_crc_err": 0,
            "collisions": 0,
            "duration_sec": 22,
            "duration_nsec": 429000000,
            "port_no": 1
        },
        {
            "rx_packets": 30,
            "tx_packets": 190,
            "rx_bytes": 2188,
            "tx_bytes": 71267,
            "rx_dropped": 0,
            "tx_dropped": 0,
            "rx_errors": 0,
            "tx_errors": 0,
            "rx_frame_err": 0,
            "rx_over_err": 0,
            "rx_crc_err": 0,
            "collisions": 0,
            "duration_sec": 22,
            "duration_nsec": 430000000,
            "port_no": 2
        },
        {
            "rx_packets": 181,
            "tx_packets": 66,
            "rx_bytes": 69289,
            "tx_bytes": 6021,
            "rx_dropped": 0,
            "tx_dropped": 0,
            "rx_errors": 0,
            "tx_errors": 0,
            "rx_frame_err": 0,
            "rx_over_err": 0,
            "rx_crc_err": 0,
            "collisions": 0,
            "duration_sec": 22,
            "duration_nsec": 430000000,
            "port_no": 3
        }
    ]
}